funuser/__init__.py
funuser/cli.py
funuser/main.py
funuser/core/__init__.py
funuser/core/security.py
funuser/database/__init__.py
funuser/database/database.py
funuser/models/__init__.py
funuser/models/user.py
funuser/routers/__init__.py
funuser/routers/user.py
funuser/schemas/__init__.py
funuser/schemas/user.py
funuser-0.1.2.dist-info/METADATA
funuser-0.1.2.dist-info/WHEEL
funuser-0.1.2.dist-info/entry_points.txt
funuser-0.1.2.dist-info/top_level.txt
funuser-0.1.2.dist-info/RECORD
